odoo/addons/l10n_ro_message_spv/README.rst
odoo/addons/l10n_ro_message_spv/__init__.py
odoo/addons/l10n_ro_message_spv/__manifest__.py
odoo/addons/l10n_ro_message_spv/data/ir_cron_data.xml
odoo/addons/l10n_ro_message_spv/i18n/l10n_ro_message_spv.pot
odoo/addons/l10n_ro_message_spv/i18n/ro.po
odoo/addons/l10n_ro_message_spv/models/__init__.py
odoo/addons/l10n_ro_message_spv/models/account_edi_xml_cius_ro.py
odoo/addons/l10n_ro_message_spv/models/account_move.py
odoo/addons/l10n_ro_message_spv/models/ciusro_document.py
odoo/addons/l10n_ro_message_spv/models/message_spv.py
odoo/addons/l10n_ro_message_spv/models/res_company.py
odoo/addons/l10n_ro_message_spv/readme/CONFIGURE.md
odoo/addons/l10n_ro_message_spv/readme/CONTRIBUTORS.md
odoo/addons/l10n_ro_message_spv/readme/DESCRIPTION.md
odoo/addons/l10n_ro_message_spv/security/ir.model.access.csv
odoo/addons/l10n_ro_message_spv/security/security.xml
odoo/addons/l10n_ro_message_spv/static/description/icon.png
odoo/addons/l10n_ro_message_spv/static/description/icon.svg
odoo/addons/l10n_ro_message_spv/static/description/index.html
odoo/addons/l10n_ro_message_spv/tests/__init__.py
odoo/addons/l10n_ro_message_spv/tests/common.py
odoo/addons/l10n_ro_message_spv/tests/invoice.zip
odoo/addons/l10n_ro_message_spv/tests/test_message_spv.py
odoo/addons/l10n_ro_message_spv/views/account_invoice.xml
odoo/addons/l10n_ro_message_spv/views/message_spv_view.xml
odoo/addons/l10n_ro_message_spv/wizard/__init__.py
odoo/addons/l10n_ro_message_spv/wizard/res_config_settings.py
odoo/addons/l10n_ro_message_spv/wizard/res_config_settings_views.xml
odoo_addon_l10n_ro_message_spv-19.0.1.13.0.dist-info/METADATA
odoo_addon_l10n_ro_message_spv-19.0.1.13.0.dist-info/WHEEL
odoo_addon_l10n_ro_message_spv-19.0.1.13.0.dist-info/top_level.txt
odoo_addon_l10n_ro_message_spv-19.0.1.13.0.dist-info/RECORD
